mdify/__init__.py
mdify/configs/blip_config.yml
mdify/configs/easy_ocr_config.yml
mdify/configs/google_vqa_config.yml
mdify/configs/layout_detection_config.yml
mdify/configs/paddle_ocr_config.yml
mdify/configs/surya_ocr_config.yml
mdify/src/__init__.py
mdify/src/extractors.py
mdify/src/layout.py
mdify/src/models.py
mdify/src/ocr.py
mdify/src/output.py
mdify/src/parsers.py
mdify/src/utils.py
mdify-0.3.2.dist-info/LICENSE
mdify-0.3.2.dist-info/METADATA
mdify-0.3.2.dist-info/WHEEL
mdify-0.3.2.dist-info/top_level.txt
mdify-0.3.2.dist-info/RECORD
