Metadata-Version: 2.2
Name: mdify
Version: 0.3.2
Summary: A powerful tool to extract text, tables, charts, and formulas from documents and convert them into Markdown format, ideal to improve LLM's accuracy and for versatile document processing.
Home-page: https://github.com/stefanodangelo/mdify
Author: Stefano D'Angelo
License: CC BY-NC 4.0
Project-URL: GitHub Repository, https://github.com/stefanodangelo/mdify
Project-URL: Documentation, https://stefanodangelo.github.io/mdify/
Classifier: Development Status :: 5 - Production/Stable
Classifier: Environment :: GPU :: NVIDIA CUDA :: 11.7
Classifier: Framework :: MkDocs
Classifier: License :: Free for non-commercial use
Classifier: Natural Language :: English
Classifier: Programming Language :: Python :: 3.11
Classifier: Topic :: Scientific/Engineering :: Artificial Intelligence
Classifier: Topic :: Software Development :: Libraries :: Python Modules
Requires-Python: >=3.8
License-File: LICENSE
Requires-Dist: pypdfium2==4.30.0
Requires-Dist: ultralytics==8.3.51
Requires-Dist: ultralyticsplus
Requires-Dist: ipykernel==6.29.5
Requires-Dist: paddlepaddle==2.6.2
Requires-Dist: paddleocr
Requires-Dist: pandas==2.2.0
Requires-Dist: tabulate==0.9.0
Requires-Dist: doclayout-yolo==0.0.3
Requires-Dist: unimernet==0.2.1
Requires-Dist: struct-eqtable==0.3.3
Requires-Dist: lmdeploy==0.6.4
Requires-Dist: omegaconf==2.3.0
Requires-Dist: supervision==0.25.1
Requires-Dist: torch==2.3.1
Requires-Dist: optimum==1.23.3
Requires-Dist: onnxruntime==1.15.1
Requires-Dist: onnx==1.16.1
Requires-Dist: surya-ocr<=0.8.0
Requires-Dist: protobuf==3.20.2
Requires-Dist: easyocr==1.7.2
Requires-Dist: pymupdf==1.25.1
Dynamic: author
Dynamic: classifier
Dynamic: description
Dynamic: description-content-type
Dynamic: home-page
Dynamic: license
Dynamic: project-url
Dynamic: requires-dist
Dynamic: requires-python
Dynamic: summary
